osxcollector/__init__.py
osxcollector/output_filters/__init__.py
osxcollector/output_filters/analyze.py
osxcollector/output_filters/exceptions.py
osxcollector/output_filters/find_blacklisted.py
osxcollector/output_filters/find_domains.py
osxcollector/output_filters/related_files.py
osxcollector/output_filters/alexa/__init__.py
osxcollector/output_filters/alexa/lookup_rankings.py
osxcollector/output_filters/base_filters/__init__.py
osxcollector/output_filters/base_filters/chain.py
osxcollector/output_filters/base_filters/output_filter.py
osxcollector/output_filters/base_filters/threat_feed.py
osxcollector/output_filters/chrome/__init__.py
osxcollector/output_filters/chrome/find_extensions.py
osxcollector/output_filters/chrome/sort_history.py
osxcollector/output_filters/firefox/__init__.py
osxcollector/output_filters/firefox/find_extensions.py
osxcollector/output_filters/firefox/sort_history.py
osxcollector/output_filters/opendns/__init__.py
osxcollector/output_filters/opendns/lookup_domains.py
osxcollector/output_filters/opendns/related_domains.py
osxcollector/output_filters/shadowserver/__init__.py
osxcollector/output_filters/shadowserver/lookup_hashes.py
osxcollector/output_filters/summary_filters/__init__.py
osxcollector/output_filters/summary_filters/html.py
osxcollector/output_filters/summary_filters/summary.py
osxcollector/output_filters/summary_filters/text.py
osxcollector/output_filters/util/__init__.py
osxcollector/output_filters/util/blacklist.py
osxcollector/output_filters/util/config.py
osxcollector/output_filters/util/dict_utils.py
osxcollector/output_filters/util/domains.py
osxcollector/output_filters/util/error_messages.py
osxcollector/output_filters/virustotal/__init__.py
osxcollector/output_filters/virustotal/lookup_domains.py
osxcollector/output_filters/virustotal/lookup_hashes.py
osxcollector/output_filters/virustotal/lookup_urls.py
tests/output_filters/__init__.py
tests/output_filters/find_blacklisted_test.py
osxcollector_output_filters-1.1.1.dist-info/LICENSE.md
osxcollector_output_filters-1.1.1.dist-info/METADATA
osxcollector_output_filters-1.1.1.dist-info/WHEEL
osxcollector_output_filters-1.1.1.dist-info/top_level.txt
osxcollector_output_filters-1.1.1.dist-info/RECORD
