Metadata-Version: 2.1
Name: osxcollector-output-filters
Version: 1.1.1
Summary: Filters that process and transform the output of OSXCollector
Home-page: https://github.com/Yelp/osxcollector_output_filters
Author: Yelp Security
Author-email: opensource@yelp.com
License: GNU General Public License
Platform: UNKNOWN
Provides: osxcollector
Requires-Dist: PyYAML (>=5.0)
Requires-Dist: threat-intel
Requires-Dist: tldextract
Requires-Dist: simplejson
Requires-Dist: six
